encoded_video/__init__.py
encoded_video/encoded_video.py
encoded_video/utils.py
encoded_video-0.0.3.dist-info/METADATA
encoded_video-0.0.3.dist-info/WHEEL
encoded_video-0.0.3.dist-info/top_level.txt
encoded_video-0.0.3.dist-info/RECORD
