Metadata-Version: 2.4
Name: encoded-video
Version: 0.0.3
Summary: Video utilities
Home-page: https://github.com/nateraw/encoded-video
Author: Nathan Raw
Author-email: naterawdata@gmail.com
Requires-Dist: av>=14.0.1
Requires-Dist: iopath
Requires-Dist: numpy
Dynamic: author
Dynamic: author-email
Dynamic: home-page
Dynamic: requires-dist
Dynamic: summary
